[{"lang": "en", "created_at": "2015-011-28T19:25:40Z", "tweet_urls": [], "entities": [], "text_en": "RT @TomBoxingAsylum: Imagine some of these fannies lived in the 40s. \"Oh, lets not bomb the German's, it's so inhuman\".  #Weirdos #BombSyria", "concepts": [], "retweet_count": 31, "id": "670685005287419906", "favorite_count": 0, "tweet_hashtags": ["Weirdos", "BombSyria"]},{"lang": "en", "created_at": "2015-011-28T18:51:09Z", "tweet_urls": [], "entities": [], "text_en": "RT @nationalowl: Mainly to annoy hipsters and leftists, can we please try and get #BombSyria trending!\n#BombSyria \n#BombSyria \n#BombSyria", "concepts": [], "retweet_count": 7, "id": "670676316916744193", "favorite_count": 0, "tweet_hashtags": ["BombSyria", "BombSyria", "BombSyria", "BombSyria"]},{"lang": "en", "created_at": "2015-011-28T21:55:53Z", "tweet_urls": ["http://twitter.com/BBCPropaganda/status/670722807731458050/photo/1"], "entities": [], "text_en": "#BombSyria, because sometimes it takes dogs to break up a cat fight https://t.co/2u6ZDzGVf4", "concepts": [], "retweet_count": 5, "id": "670722807731458050", "favorite_count": 6, "tweet_hashtags": ["BombSyria"]},{"lang": "en", "created_at": "2015-011-28T21:18:26Z", "tweet_urls": [], "entities": [], "text_en": "RT @uwakreations: OH! Please @jeremycorbyn @JeremyCorbyn4PM STAND your ground! We r FULLY behind you! We WILL NOT #BombSyria #DontBombSyria\u2026", "concepts": [], "retweet_count": 8, "id": "670713382748729345", "favorite_count": 0, "tweet_hashtags": ["BombSyria", "DontBombSyria"]},{"lang": "en", "created_at": "2015-011-28T19:00:53Z", "tweet_urls": [], "entities": [], "text_en": "Supporting bombing is easy from a distance. That's why you never see a pro-bomb rally #DontBombSyria #BombSyria https://t.co/RP1yekJJHh", "concepts": [], "retweet_count": 0, "id": "670678765882748929", "favorite_count": 0, "tweet_hashtags": ["DontBombSyria", "BombSyria"]},{"lang": "en", "created_at": "2015-011-28T18:47:37Z", "tweet_urls": [], "entities": [], "text_en": "#DontBombSyria vs #bombsyria\n\nTwar of civic society. The UK govt can choose a convenient side and say, \"it was the people.\"", "concepts": [], "retweet_count": 0, "id": "670675428399558656", "favorite_count": 0, "tweet_hashtags": ["DontBombSyria", "bombsyria"]},{"lang": "en", "created_at": "2015-011-28T20:19:45Z", "tweet_urls": [], "entities": [], "text_en": "Anyone that doesn't want to airstrike terrorists in Syria must have sympathy for daesh (ISIS)? #BombSyria", "concepts": [], "retweet_count": 2, "id": "670698617057996800", "favorite_count": 0, "tweet_hashtags": ["BombSyria"]},{"lang": "en", "created_at": "2015-011-28T18:29:46Z", "tweet_urls": [], "entities": [], "text_en": "Should we bomb Syria or not? #DontBombSyria  #BombSyria", "concepts": [], "retweet_count": 1, "id": "670670937004580866", "favorite_count": 1, "tweet_hashtags": ["DontBombSyria", "BombSyria"]},{"lang": "en", "created_at": "2015-011-28T19:00:45Z", "tweet_urls": [], "entities": [], "text_en": "RT @ImportantStufff: #DontBombSyria IF it kills innocent people. If it doesn't and it kills #Isis militants then #BombSyria. Hoping for pea\u2026", "concepts": [], "retweet_count": 11, "id": "670678735293693953", "favorite_count": 0, "tweet_hashtags": ["DontBombSyria", "Isis", "BombSyria"]},{"lang": "en", "created_at": "2015-011-28T19:12:03Z", "tweet_urls": ["https://twitter.com/LabourOutOfScot/status/670367402509672448"], "entities": [], "text_en": "RT @rebroger: UK MSM trying to convince British public that they support #BombSyria when clearly they don't! #DontBombSyria  https://t.co/i\u2026", "concepts": [], "retweet_count": 5, "id": "670681578373296129", "favorite_count": 0, "tweet_hashtags": ["BombSyria", "DontBombSyria"]},{"lang": "en", "created_at": "2015-011-28T20:38:42Z", "tweet_urls": [], "entities": [], "text_en": "How come I have never seen #Rocky III omg @HulkHogan as #thunderlips ARE U KIDDING ME!!!! #LifeIsWorthLiving #underarock #BombSyria", "concepts": [], "retweet_count": 0, "id": "670703384345772032", "favorite_count": 0, "tweet_hashtags": ["Rocky", "thunderlips", "LifeIsWorthLiving", "underarock", "BombSyria"]},{"lang": "en", "created_at": "2015-011-28T21:56:35Z", "tweet_urls": ["http://twitter.com/BBCPropaganda/status/670722807731458050/photo/1"], "entities": [], "text_en": "RT @BBCPropaganda: #BombSyria, because sometimes it takes dogs to break up a cat fight https://t.co/2u6ZDzGVf4", "concepts": [], "retweet_count": 5, "id": "670722982482976768", "favorite_count": 0, "tweet_hashtags": ["BombSyria"]},{"lang": "en", "created_at": "2015-011-28T18:58:23Z", "tweet_urls": [], "entities": [], "text_en": "To #bombsyria is to create MORE hate, MORE pain, MORE broken lives. Who would want that? #DontBombSyria", "concepts": [], "retweet_count": 0, "id": "670678136686780416", "favorite_count": 0, "tweet_hashtags": ["bombsyria", "DontBombSyria"]},{"lang": "en", "created_at": "2015-011-28T22:13:50Z", "tweet_urls": [], "entities": [], "text_en": "Thinking through the endgame is a critical part of any wartime strategy.Will it help deliver long-term stability?\u201d #BombSyria #DontBombSyria", "concepts": [], "retweet_count": 0, "id": "670727325605056512", "favorite_count": 1, "tweet_hashtags": ["BombSyria", "DontBombSyria"]},{"lang": "en", "created_at": "2015-011-28T21:26:02Z", "tweet_urls": [], "entities": [], "text_en": "RT @chrisclayton98: To al the members of the #labour shadow cabinet. You clearly believe this is a price worth paying #BombSyria. https://t\u2026", "concepts": [], "retweet_count": 5, "id": "670715296794214400", "favorite_count": 0, "tweet_hashtags": ["labour", "BombSyria"]},{"lang": "en", "created_at": "2015-011-28T19:00:21Z", "tweet_urls": [], "entities": [], "text_en": "RT @_m0zzaaaa: Oh yeah, because praying for love and peace is really going to defeat ISIS... #BombSyria", "concepts": [], "retweet_count": 31, "id": "670678634798026752", "favorite_count": 0, "tweet_hashtags": ["BombSyria"]},{"lang": "en", "created_at": "2015-011-28T19:00:01Z", "tweet_urls": [], "entities": [], "text_en": "Alternative to #bombsyria -for our govt to stop cosying up to arms dealers and funding overseas military and militant action #DontBombSyria", "concepts": [], "retweet_count": 1, "id": "670678549070749700", "favorite_count": 0, "tweet_hashtags": ["bombsyria", "DontBombSyria"]},{"lang": "en", "created_at": "2015-011-28T18:48:39Z", "tweet_urls": [], "entities": [], "text_en": "RT @MrPolyatheist: If you won't #BombSyria today, you may have to bomb your own towns and neighborhoods tomorrow. Ideologies know no border\u2026", "concepts": [], "retweet_count": 34, "id": "670675690254110721", "favorite_count": 0, "tweet_hashtags": ["BombSyria"]},{"lang": "en", "created_at": "2015-011-28T19:07:17Z", "tweet_urls": ["https://twitter.com/LabourOutOfScot/status/670367402509672448"], "entities": [], "text_en": "UK MSM trying to convince British public that they support #BombSyria when clearly they don't! #DontBombSyria  https://t.co/iFy5GhzBzZ", "concepts": [], "retweet_count": 5, "id": "670680379020455936", "favorite_count": 2, "tweet_hashtags": ["BombSyria", "DontBombSyria"]},{"lang": "en", "created_at": "2015-011-28T18:30:38Z", "tweet_urls": [], "entities": [], "text_en": "let's end this. #BombSyria", "concepts": [], "retweet_count": 0, "id": "670671156605820928", "favorite_count": 0, "tweet_hashtags": ["BombSyria"]},{"lang": "en", "created_at": "2015-011-28T21:01:38Z", "tweet_urls": [], "entities": [], "text_en": "War on #ISIS !! What is the end game ?? \u201cThe test of policy is how it ends, not how it begins.\u201d-Henry Kissinger #BombSyria . #DontBombSyria", "concepts": [], "retweet_count": 0, "id": "670709154642837505", "favorite_count": 1, "tweet_hashtags": ["ISIS", "BombSyria", "DontBombSyria"]},{"lang": "en", "created_at": "2015-011-28T18:42:29Z", "tweet_urls": [], "entities": [], "text_en": "Do you think we should expand bombing operations into Syria? #BombSyria #DontBombSyria #ISIS #terroristattack", "concepts": [], "retweet_count": 1, "id": "670674136621019136", "favorite_count": 1, "tweet_hashtags": ["BombSyria", "DontBombSyria", "ISIS", "terroristattack"]},{"lang": "en", "created_at": "2015-011-28T22:22:38Z", "tweet_urls": ["http://twitter.com/BBCPropaganda/status/670722807731458050/photo/1"], "entities": [], "text_en": "RT @BBCPropaganda: #BombSyria, because sometimes it takes dogs to break up a cat fight https://t.co/2u6ZDzGVf4", "concepts": [], "retweet_count": 5, "id": "670729538121412608", "favorite_count": 0, "tweet_hashtags": ["BombSyria"]},{"lang": "en", "created_at": "2015-011-28T18:21:41Z", "tweet_urls": [], "entities": [], "text_en": "RT @kurtcocaine93: Destroying ISIS is the only solution. The #RegressiveLeft standing in the way of progress again #BombSyria", "concepts": [], "retweet_count": 22, "id": "670668902154784771", "favorite_count": 0, "tweet_hashtags": ["RegressiveLeft", "BombSyria"]},{"lang": "en", "created_at": "2015-011-28T19:30:01Z", "tweet_urls": [], "entities": [], "text_en": "RT @John_Donald89: @jeremycorbyn what a complete fool you live in a fantasy land wake up fool #TheWorldisWatching #uk and your make us look\u2026", "concepts": [], "retweet_count": 2, "id": "670686098016894976", "favorite_count": 0, "tweet_hashtags": ["TheWorldisWatching", "uk", "bombsyria"]},{"lang": "en", "created_at": "2015-011-28T18:35:49Z", "tweet_urls": [], "entities": [], "text_en": "RT @_DJSavage: When the US bombed Hiroshima, it pretty much ended WW2. #BombSyria", "concepts": [], "retweet_count": 4, "id": "670672457825714176", "favorite_count": 0, "tweet_hashtags": ["BombSyria"]},{"lang": "en", "created_at": "2015-011-28T19:03:58Z", "tweet_urls": [], "entities": [], "text_en": "RT @pmcd_82: Alternative to #bombsyria -for our govt to stop cosying up to arms dealers and funding overseas military and militant action #\u2026", "concepts": [], "retweet_count": 1, "id": "670679544970522625", "favorite_count": 0, "tweet_hashtags": ["bombsyria", "DontBombSyria"]},{"lang": "en", "created_at": "2015-011-28T19:12:23Z", "tweet_urls": ["https://twitter.com/LabourOutOfScot/status/670367402509672448"], "entities": [], "text_en": "RT @rebroger: UK MSM trying to convince British public that they support #BombSyria when clearly they don't! #DontBombSyria  https://t.co/i\u2026", "concepts": [], "retweet_count": 5, "id": "670681662381031425", "favorite_count": 0, "tweet_hashtags": ["BombSyria", "DontBombSyria"]},{"lang": "en", "created_at": "2015-011-28T18:16:21Z", "tweet_urls": [], "entities": [], "text_en": "@angelaeagle @tom_watson @andyburnhammp @MaryCreaghMP If we bomb ISIS in Iraq whats the difference in attacking them in #Syria? #BombSyria", "concepts": [], "retweet_count": 0, "id": "670667558912196608", "favorite_count": 0, "tweet_hashtags": ["Syria", "BombSyria"]},{"lang": "en", "created_at": "2015-011-28T23:36:05Z", "tweet_urls": [], "entities": [], "text_en": "RT @Bekki_R_92: #DontBombSyria / #BombSyria debate isn't black and white. Not bombing will make things worse, but so will bombing/funding t\u2026", "concepts": [], "retweet_count": 11, "id": "670748023165755392", "favorite_count": 0, "tweet_hashtags": ["DontBombSyria", "BombSyria"]},{"lang": "en", "created_at": "2015-011-28T21:59:41Z", "tweet_urls": ["http://twitter.com/BBCPropaganda/status/670722807731458050/photo/1"], "entities": [], "text_en": "RT @BBCPropaganda: #BombSyria, because sometimes it takes dogs to break up a cat fight https://t.co/2u6ZDzGVf4", "concepts": [], "retweet_count": 5, "id": "670723766117355520", "favorite_count": 0, "tweet_hashtags": ["BombSyria"]},{"lang": "en", "created_at": "2015-011-28T18:52:21Z", "tweet_urls": [], "entities": [], "text_en": "RT @PeteRoberts639: The French have asked us for our help.Remember the bravery of the French Resistance during WW2\n\n#Paris\n#BombSyria https\u2026", "concepts": [], "retweet_count": 9, "id": "670676620282363904", "favorite_count": 0, "tweet_hashtags": ["Paris", "BombSyria"]},{"lang": "en", "created_at": "2015-011-28T18:58:18Z", "tweet_urls": [], "entities": [], "text_en": "Reminder: options exist beyond #BombSyria and #DontBombSyria...but those are more complex and don't involve as much self congratulation", "concepts": [], "retweet_count": 4, "id": "670678119448248321", "favorite_count": 5, "tweet_hashtags": ["BombSyria", "DontBombSyria"]},{"lang": "en", "created_at": "2015-011-28T18:49:05Z", "tweet_urls": [], "entities": [], "text_en": "RT @PeteRoberts639: The French have asked us for our help.Remember the bravery of the French Resistance during WW2\n\n#Paris\n#BombSyria https\u2026", "concepts": [], "retweet_count": 9, "id": "670675797506727936", "favorite_count": 0, "tweet_hashtags": ["Paris", "BombSyria"]},{"lang": "en", "created_at": "2015-011-28T21:01:05Z", "tweet_urls": [], "entities": [], "text_en": "OH! Please @jeremycorbyn @JeremyCorbyn4PM STAND your ground! We r FULLY behind you! We WILL NOT #BombSyria #DontBombSyria @PeoplesMomentum", "concepts": [], "retweet_count": 8, "id": "670709015974907904", "favorite_count": 11, "tweet_hashtags": ["BombSyria", "DontBombSyria"]},{"lang": "en", "created_at": "2015-011-28T21:21:51Z", "tweet_urls": [], "entities": [], "text_en": "RT @chrisclayton98: To al the members of the #labour shadow cabinet. You clearly believe this is a price worth paying #BombSyria. https://t\u2026", "concepts": [], "retweet_count": 5, "id": "670714245168934912", "favorite_count": 0, "tweet_hashtags": ["labour", "BombSyria"]},{"lang": "en", "created_at": "2015-011-28T22:52:42Z", "tweet_urls": [], "entities": [], "text_en": "RT @uwakreations: OH! Please @jeremycorbyn @JeremyCorbyn4PM STAND your ground! We r FULLY behind you! We WILL NOT #BombSyria #DontBombSyria\u2026", "concepts": [], "retweet_count": 8, "id": "670737106411589632", "favorite_count": 0, "tweet_hashtags": ["BombSyria", "DontBombSyria"]},{"lang": "en", "created_at": "2015-011-28T21:16:34Z", "tweet_urls": [], "entities": [], "text_en": "RT @shaunynev: Anyone that doesn't want to airstrike terrorists in Syria must have sympathy for daesh (ISIS)? #BombSyria", "concepts": [], "retweet_count": 2, "id": "670712913448075264", "favorite_count": 0, "tweet_hashtags": ["BombSyria"]},{"lang": "en", "created_at": "2015-011-28T18:26:32Z", "tweet_urls": [], "entities": [], "text_en": "#BombSyria until they stop harbouring terrorism.", "concepts": [], "retweet_count": 0, "id": "670670124395950080", "favorite_count": 0, "tweet_hashtags": ["BombSyria"]},{"lang": "en", "created_at": "2015-011-28T18:48:44Z", "tweet_urls": [], "entities": [], "text_en": "RT @kurtcocaine93: Destroying ISIS is the only solution. The #RegressiveLeft standing in the way of progress again #BombSyria", "concepts": [], "retweet_count": 22, "id": "670675709661192192", "favorite_count": 0, "tweet_hashtags": ["RegressiveLeft", "BombSyria"]},{"lang": "en", "created_at": "2015-011-28T19:13:10Z", "tweet_urls": ["https://twitter.com/LabourOutOfScot/status/670367402509672448"], "entities": [], "text_en": "RT @rebroger: UK MSM trying to convince British public that they support #BombSyria when clearly they don't! #DontBombSyria  https://t.co/i\u2026", "concepts": [], "retweet_count": 5, "id": "670681859936919557", "favorite_count": 0, "tweet_hashtags": ["BombSyria", "DontBombSyria"]},{"lang": "en", "created_at": "2015-011-28T21:03:00Z", "tweet_urls": [], "entities": [], "text_en": "RT @uwakreations: OH! Please @jeremycorbyn @JeremyCorbyn4PM STAND your ground! We r FULLY behind you! We WILL NOT #BombSyria #DontBombSyria\u2026", "concepts": [], "retweet_count": 8, "id": "670709498181500928", "favorite_count": 0, "tweet_hashtags": ["BombSyria", "DontBombSyria"]},{"lang": "en", "created_at": "2015-011-28T18:21:56Z", "tweet_urls": [], "entities": [], "text_en": "RT @BrexitBulldog: So shocked #DontBombSyria is trending. How anyone could be opposed to the destruction of a terrorist regime is beyond me\u2026", "concepts": [], "retweet_count": 34, "id": "670668965895675904", "favorite_count": 0, "tweet_hashtags": ["DontBombSyria", "BombSyria", "BombIS"]},{"lang": "en", "created_at": "2015-011-28T20:40:52Z", "tweet_urls": ["http://youtu.be/3PPsZQnBIrk"], "entities": [], "text_en": "Thousands rally in #UK against bombing #Syria.\n@AJEnglish @NeaveBarker #SyriaAirStrikes #SyrianRefugees #BombSyria  https://t.co/lIiRBpYXzc", "concepts": [], "retweet_count": 0, "id": "670703930712694784", "favorite_count": 0, "tweet_hashtags": ["UK", "Syria", "SyriaAirStrikes", "SyrianRefugees", "BombSyria"]},{"lang": "en", "created_at": "2015-011-28T18:52:27Z", "tweet_urls": [], "entities": [], "text_en": "RT @BrexitBulldog: So shocked #DontBombSyria is trending. How anyone could be opposed to the destruction of a terrorist regime is beyond me\u2026", "concepts": [], "retweet_count": 34, "id": "670676646278635520", "favorite_count": 0, "tweet_hashtags": ["DontBombSyria", "BombSyria", "BombIS"]},{"lang": "en", "created_at": "2015-011-28T20:43:23Z", "tweet_urls": [], "entities": [], "text_en": "The #BombSyria hashtag is disgusting, bombing for peace and murdering to save lives is not how it works", "concepts": [], "retweet_count": 0, "id": "670704564375539712", "favorite_count": 3, "tweet_hashtags": ["BombSyria"]},{"lang": "en", "created_at": "2015-011-28T18:59:11Z", "tweet_urls": [], "entities": [], "text_en": "If you #bombsyria you will be helping Cammers and Barry O achieve their target of pretending to end IS whilst getting rid of Assad!", "concepts": [], "retweet_count": 0, "id": "670678338676121600", "favorite_count": 0, "tweet_hashtags": ["bombsyria"]},{"lang": "en", "created_at": "2015-011-28T19:52:46Z", "tweet_urls": [], "entities": [], "text_en": "A1st world country deciding to #BombSyria is like your parents deciding that they'll go take a shit in a homeless mans tent #DontBombSyria", "concepts": [], "retweet_count": 0, "id": "670691825259253760", "favorite_count": 0, "tweet_hashtags": ["BombSyria", "DontBombSyria"]},{"lang": "en", "created_at": "2015-011-28T20:15:19Z", "tweet_urls": [], "entities": [], "text_en": "A lot of my Customers see no point us joining the #BombSyria @jeremycorbyn https://t.co/0IVPrJ83Ay", "concepts": [], "retweet_count": 0, "id": "670697498999193600", "favorite_count": 0, "tweet_hashtags": ["BombSyria"]},{"lang": "en", "created_at": "2015-011-28T22:36:24Z", "tweet_urls": ["http://twitter.com/BBCPropaganda/status/670722807731458050/photo/1"], "entities": [], "text_en": "RT @BBCPropaganda: #BombSyria, because sometimes it takes dogs to break up a cat fight https://t.co/2u6ZDzGVf4", "concepts": [], "retweet_count": 5, "id": "670733002910101505", "favorite_count": 0, "tweet_hashtags": ["BombSyria"]},{"lang": "en", "created_at": "2015-011-28T19:10:10Z", "tweet_urls": ["https://twitter.com/LabourOutOfScot/status/670367402509672448"], "entities": [], "text_en": "RT @rebroger: UK MSM trying to convince British public that they support #BombSyria when clearly they don't! #DontBombSyria  https://t.co/i\u2026", "concepts": [], "retweet_count": 5, "id": "670681101929750528", "favorite_count": 0, "tweet_hashtags": ["BombSyria", "DontBombSyria"]},{"lang": "en", "created_at": "2015-011-28T19:57:48Z", "tweet_urls": [], "entities": [], "text_en": "RT @jbralston: Reminder: options exist beyond #BombSyria and #DontBombSyria...but those are more complex and don't involve as much self con\u2026", "concepts": [], "retweet_count": 4, "id": "670693091511136256", "favorite_count": 0, "tweet_hashtags": ["BombSyria", "DontBombSyria"]},{"lang": "en", "created_at": "2015-011-28T21:51:01Z", "tweet_urls": [], "entities": [], "text_en": "RT @uwakreations: OH! Please @jeremycorbyn @JeremyCorbyn4PM STAND your ground! We r FULLY behind you! We WILL NOT #BombSyria #DontBombSyria\u2026", "concepts": [], "retweet_count": 8, "id": "670721583057604612", "favorite_count": 0, "tweet_hashtags": ["BombSyria", "DontBombSyria"]},{"lang": "en", "created_at": "2015-011-28T19:56:03Z", "tweet_urls": [], "entities": [], "text_en": "@AdinaEnache08 We can't just stop the war around the world, but we can protect what's ours now,our society, our lives and #peace #BombSyria", "concepts": [], "retweet_count": 0, "id": "670692649331007488", "favorite_count": 1, "tweet_hashtags": ["peace", "BombSyria"]},{"lang": "en", "created_at": "2015-011-28T21:57:43Z", "tweet_urls": ["http://twitter.com/BBCPropaganda/status/670722807731458050/photo/1"], "entities": [], "text_en": "RT @BBCPropaganda: #BombSyria, because sometimes it takes dogs to break up a cat fight https://t.co/2u6ZDzGVf4", "concepts": [], "retweet_count": 5, "id": "670723270375665666", "favorite_count": 0, "tweet_hashtags": ["BombSyria"]},{"lang": "en", "created_at": "2015-011-28T19:51:14Z", "tweet_urls": [], "entities": [], "text_en": "Deport the kebab from Europe and the West, then turn the Middle East into a sandbox. The rest of the world will be a safer place. #BombSyria", "concepts": [], "retweet_count": 0, "id": "670691439957839872", "favorite_count": 2, "tweet_hashtags": ["BombSyria"]},{"lang": "en", "created_at": "2015-011-28T20:09:46Z", "tweet_urls": [], "entities": [], "text_en": "RT @ImportantStufff: #DontBombSyria IF it kills innocent people. If it doesn't and it kills #Isis militants then #BombSyria. Hoping for pea\u2026", "concepts": [], "retweet_count": 11, "id": "670696100853075968", "favorite_count": 0, "tweet_hashtags": ["DontBombSyria", "Isis", "BombSyria"]},{"lang": "en", "created_at": "2015-011-28T19:34:58Z", "tweet_urls": [], "entities": [], "text_en": "RT @jbralston: Reminder: options exist beyond #BombSyria and #DontBombSyria...but those are more complex and don't involve as much self con\u2026", "concepts": [], "retweet_count": 4, "id": "670687345922805760", "favorite_count": 0, "tweet_hashtags": ["BombSyria", "DontBombSyria"]},{"lang": "en", "created_at": "2015-011-28T20:23:45Z", "tweet_urls": [], "entities": [], "text_en": "@_Milkybar_ your right.. We should let Isis carry on with their killing and raping of innocent woman and children. You fucktard! #bombsyria", "concepts": [], "retweet_count": 1, "id": "670699621941907456", "favorite_count": 0, "tweet_hashtags": ["bombsyria"]},{"lang": "en", "created_at": "2015-011-28T21:21:14Z", "tweet_urls": [], "entities": [], "text_en": "RT @uwakreations: OH! Please @jeremycorbyn @JeremyCorbyn4PM STAND your ground! We r FULLY behind you! We WILL NOT #BombSyria #DontBombSyria\u2026", "concepts": [], "retweet_count": 8, "id": "670714089551888384", "favorite_count": 0, "tweet_hashtags": ["BombSyria", "DontBombSyria"]},{"lang": "en", "created_at": "2015-011-28T18:29:12Z", "tweet_urls": ["https://twitter.com/daudit10/status/670244886973673472"], "entities": [], "text_en": "How are we letting brown people get away with this??\n#BombSyria https://t.co/fXh5Jpuqas", "concepts": [], "retweet_count": 0, "id": "670670792506626048", "favorite_count": 0, "tweet_hashtags": ["BombSyria"]},{"lang": "en", "created_at": "2015-011-28T18:57:28Z", "tweet_urls": [], "entities": [], "text_en": "RT @ImportantStufff: #DontBombSyria IF it kills innocent people. If it doesn't and it kills #Isis militants then #BombSyria. Hoping for pea\u2026", "concepts": [], "retweet_count": 11, "id": "670677908856414208", "favorite_count": 0, "tweet_hashtags": ["DontBombSyria", "Isis", "BombSyria"]},{"lang": "en", "created_at": "2015-011-28T18:15:04Z", "tweet_urls": [], "entities": [], "text_en": "@dystopia47 You Must Not Read Or View The News Ever - #ISIS Is Based In Syria Since Day One. Wake Up #ISIS Worldwide Already. #BombSyria", "concepts": [], "retweet_count": 0, "id": "670667239037734912", "favorite_count": 0, "tweet_hashtags": ["ISIS", "ISIS", "BombSyria"]},{"lang": "en", "created_at": "2015-011-28T19:07:38Z", "tweet_urls": [], "entities": [], "text_en": "#BombSyria #EntanteCordial #FreeWorldAtRisk - just since the opposite is supposedly trending - #SilentMajority", "concepts": [], "retweet_count": 0, "id": "670680467503468544", "favorite_count": 0, "tweet_hashtags": ["BombSyria", "EntanteCordial", "FreeWorldAtRisk", "SilentMajority"]},{"lang": "en", "created_at": "2015-011-28T20:47:45Z", "tweet_urls": [], "entities": [], "text_en": "The fact the #BombSyria hashtag is trending literally disgusts me.", "concepts": [], "retweet_count": 0, "id": "670705661337014274", "favorite_count": 2, "tweet_hashtags": ["BombSyria"]},{"lang": "en", "created_at": "2015-011-28T18:39:42Z", "tweet_urls": [], "entities": [], "text_en": "RT @Gi3MO_: So, if a couple englishmen went to (say) USA and killed a hundred or so people, they'd be justified in blowing up the UK? #bomb\u2026", "concepts": [], "retweet_count": 2, "id": "670673437191442433", "favorite_count": 0, "tweet_hashtags": ["bombsyria", "logic"]},{"lang": "en", "created_at": "2015-011-28T21:05:47Z", "tweet_urls": [], "entities": [], "text_en": "RT @chrisclayton98: To al the members of the #labour shadow cabinet. You clearly believe this is a price worth paying #BombSyria. https://t\u2026", "concepts": [], "retweet_count": 5, "id": "670710201847291904", "favorite_count": 0, "tweet_hashtags": ["labour", "BombSyria"]},{"lang": "en", "created_at": "2015-011-28T18:48:34Z", "tweet_urls": [], "entities": [], "text_en": "RT @SirJenkinson: Bleating idiots saying #DontBombSyria. Clearly taken complete leave of their senses. It's time to #BombSyria.", "concepts": [], "retweet_count": 15, "id": "670675670213763072", "favorite_count": 0, "tweet_hashtags": ["DontBombSyria", "BombSyria"]},{"lang": "en", "created_at": "2015-011-28T18:58:08Z", "tweet_urls": [], "entities": [], "text_en": "RT @Bekki_R_92: #DontBombSyria / #BombSyria debate isn't black and white. Not bombing will make things worse, but so will bombing/funding t\u2026", "concepts": [], "retweet_count": 11, "id": "670678076464996352", "favorite_count": 0, "tweet_hashtags": ["DontBombSyria", "BombSyria"]},{"lang": "en", "created_at": "2015-011-28T19:28:14Z", "tweet_urls": [], "entities": [], "text_en": "RT @Jez_55: Her Majesty's opposition is a threat to national security. #cowards #pacifists @UKLabour #BombSyria Root out UK terrorists now!\u2026", "concepts": [], "retweet_count": 1, "id": "670685651646418946", "favorite_count": 0, "tweet_hashtags": ["cowards", "pacifists", "BombSyria", "Disgrace"]},{"lang": "en", "created_at": "2015-011-28T18:27:38Z", "tweet_urls": [], "entities": [], "text_en": "RT @BrexitBulldog: So shocked #DontBombSyria is trending. How anyone could be opposed to the destruction of a terrorist regime is beyond me\u2026", "concepts": [], "retweet_count": 34, "id": "670670400863383552", "favorite_count": 0, "tweet_hashtags": ["DontBombSyria", "BombSyria", "BombIS"]},{"lang": "en", "created_at": "2015-011-28T22:19:33Z", "tweet_urls": [], "entities": [], "text_en": "RT @tuco_tuco: This is BAE systems share price over the last month. BAE systems is the UKs biggest weapons manufacturer \n#BombSyria https:/\u2026", "concepts": [], "retweet_count": 13, "id": "670728764071010304", "favorite_count": 0, "tweet_hashtags": ["BombSyria"]},{"lang": "en", "created_at": "2015-011-28T21:23:23Z", "tweet_urls": [], "entities": [], "text_en": "RT @uwakreations: OH! Please @jeremycorbyn @JeremyCorbyn4PM STAND your ground! We r FULLY behind you! We WILL NOT #BombSyria #DontBombSyria\u2026", "concepts": [], "retweet_count": 8, "id": "670714629270708224", "favorite_count": 0, "tweet_hashtags": ["BombSyria", "DontBombSyria"]},{"lang": "en", "created_at": "2015-011-28T19:30:02Z", "tweet_urls": [], "entities": [], "text_en": "RT @ImportantStufff: #DontBombSyria IF it kills innocent people. If it doesn't and it kills #Isis militants then #BombSyria. Hoping for pea\u2026", "concepts": [], "retweet_count": 11, "id": "670686104375398400", "favorite_count": 0, "tweet_hashtags": ["DontBombSyria", "Isis", "BombSyria"]},{"lang": "en", "created_at": "2015-011-28T19:00:59Z", "tweet_urls": [], "entities": [], "text_en": "RT @BrexitBulldog: So shocked #DontBombSyria is trending. How anyone could be opposed to the destruction of a terrorist regime is beyond me\u2026", "concepts": [], "retweet_count": 34, "id": "670678791782559744", "favorite_count": 0, "tweet_hashtags": ["DontBombSyria", "BombSyria", "BombIS"]},{"lang": "en", "created_at": "2015-011-28T22:17:43Z", "tweet_urls": [], "entities": [], "text_en": "If #Labour MPs support Cameron's #BombSyria it will be a dark day. @jeremycorbyn needs to sort his leadership out, but on this he's right", "concepts": [], "retweet_count": 0, "id": "670728301514792960", "favorite_count": 0, "tweet_hashtags": ["Labour", "BombSyria"]},{"lang": "en", "created_at": "2015-011-28T20:33:55Z", "tweet_urls": [], "entities": [], "text_en": "Those @UKLabour MPs who thought liar Cameron had made a compelling case to #BombSyria are in wrong party. #DontBombSyria #WeStandWithCorbyn", "concepts": [], "retweet_count": 0, "id": "670702178487635968", "favorite_count": 1, "tweet_hashtags": ["BombSyria", "DontBombSyria", "WeStandWithCorbyn"]},{"lang": "en", "created_at": "2015-011-28T21:08:05Z", "tweet_urls": [], "entities": [], "text_en": "RT @coznova23: #BombSyria it's time to kill eradicate ISIS and the #jihadi bastards", "concepts": [], "retweet_count": 2, "id": "670710777343574016", "favorite_count": 0, "tweet_hashtags": ["BombSyria", "jihadi"]},{"lang": "en", "created_at": "2015-011-28T18:50:48Z", "tweet_urls": [], "entities": [], "text_en": "RT @BrexitBulldog: So shocked #DontBombSyria is trending. How anyone could be opposed to the destruction of a terrorist regime is beyond me\u2026", "concepts": [], "retweet_count": 34, "id": "670676228588875777", "favorite_count": 0, "tweet_hashtags": ["DontBombSyria", "BombSyria", "BombIS"]},{"lang": "en", "created_at": "2015-011-28T18:49:47Z", "tweet_urls": [], "entities": [], "text_en": "#DontBombSyria #BombSyria  the question should be which is the bigger crime, bombing in syria, or doing nothing? Either way people will die", "concepts": [], "retweet_count": 1, "id": "670675972593729540", "favorite_count": 1, "tweet_hashtags": ["DontBombSyria", "BombSyria"]},{"lang": "en", "created_at": "2015-011-28T23:40:27Z", "tweet_urls": [], "entities": [], "text_en": "RT @Bekki_R_92: #DontBombSyria / #BombSyria debate isn't black and white. Not bombing will make things worse, but so will bombing/funding t\u2026", "concepts": [], "retweet_count": 11, "id": "670749123612643329", "favorite_count": 0, "tweet_hashtags": ["DontBombSyria", "BombSyria"]},{"lang": "en", "created_at": "2015-011-28T19:55:30Z", "tweet_urls": [], "entities": [], "text_en": "To #BombSyria or #DontBombSyria \nthe world we live in though.", "concepts": [], "retweet_count": 0, "id": "670692510604378113", "favorite_count": 0, "tweet_hashtags": ["BombSyria", "DontBombSyria"]},{"lang": "en", "created_at": "2015-011-28T19:01:13Z", "tweet_urls": [], "entities": [], "text_en": "RT @realyosefstein: #BombSyria. And #ArmTheKurds now.", "concepts": [], "retweet_count": 5, "id": "670678852579024896", "favorite_count": 0, "tweet_hashtags": ["BombSyria", "ArmTheKurds"]},{"lang": "en", "created_at": "2015-011-28T22:19:56Z", "tweet_urls": [], "entities": [], "text_en": "To the left disagreement #DontBombSyria don't you want to end terrorism by isis? @Number10gov I support #BombSyria", "concepts": [], "retweet_count": 0, "id": "670728860858720256", "favorite_count": 0, "tweet_hashtags": ["DontBombSyria", "BombSyria"]},{"lang": "en", "created_at": "2015-011-28T19:57:03Z", "tweet_urls": [], "entities": [], "text_en": "RT @ImportantStufff: #DontBombSyria IF it kills innocent people. If it doesn't and it kills #Isis militants then #BombSyria. Hoping for pea\u2026", "concepts": [], "retweet_count": 11, "id": "670692901010173953", "favorite_count": 0, "tweet_hashtags": ["DontBombSyria", "Isis", "BombSyria"]},{"lang": "en", "created_at": "2015-011-28T19:44:06Z", "tweet_urls": [], "entities": [], "text_en": "get real @jeremycorbyn it's time to #BombSyria , leave the #hippydippy shit alone and face reality !!!", "concepts": [], "retweet_count": 0, "id": "670689642111492096", "favorite_count": 0, "tweet_hashtags": ["BombSyria", "hippydippy"]},{"lang": "en", "created_at": "2015-011-28T18:59:29Z", "tweet_urls": [], "entities": [], "text_en": "@nationalowl \"To fuck the lefties and hipsters off, tweet #BombSyria\" Oh...it would be my absolute pleasure \ud83d\ude0a\n\n#BombSyria \n#BombSyria", "concepts": [], "retweet_count": 0, "id": "670678413468958720", "favorite_count": 0, "tweet_hashtags": ["BombSyria", "BombSyria", "BombSyria"]},{"lang": "en", "created_at": "2015-011-28T21:00:48Z", "tweet_urls": [], "entities": [], "text_en": "To al the members of the #labour shadow cabinet. You clearly believe this is a price worth paying #BombSyria. https://t.co/8beMf8shZX", "concepts": [], "retweet_count": 5, "id": "670708947096072193", "favorite_count": 4, "tweet_hashtags": ["labour", "BombSyria"]},{"lang": "en", "created_at": "2015-011-28T20:43:45Z", "tweet_urls": [], "entities": [], "text_en": "all who want to #BombSyria, you are to become murderers of civilian life. afflicting1000's of people to the exact criteria IS recruit from.", "concepts": [], "retweet_count": 0, "id": "670704653823291396", "favorite_count": 1, "tweet_hashtags": ["BombSyria"]},{"lang": "en", "created_at": "2015-011-28T18:50:12Z", "tweet_urls": [], "entities": [], "text_en": "RT @TomBoxingAsylum: Imagine some of these fannies lived in the 40s. \"Oh, lets not bomb the German's, it's so inhuman\".  #Weirdos #BombSyria", "concepts": [], "retweet_count": 31, "id": "670676078818680832", "favorite_count": 0, "tweet_hashtags": ["Weirdos", "BombSyria"]},{"lang": "en", "created_at": "2015-011-28T22:25:52Z", "tweet_urls": [], "entities": [], "text_en": "RT @chrisclayton98: To al the members of the #labour shadow cabinet. You clearly believe this is a price worth paying #BombSyria. https://t\u2026", "concepts": [], "retweet_count": 5, "id": "670730354341388288", "favorite_count": 0, "tweet_hashtags": ["labour", "BombSyria"]},{"lang": "en", "created_at": "2015-011-28T18:44:58Z", "tweet_urls": [], "entities": [], "text_en": "RT @nationalowl: Mainly to annoy hipsters and leftists, can we please try and get #BombSyria trending!\n#BombSyria \n#BombSyria \n#BombSyria", "concepts": [], "retweet_count": 7, "id": "670674762423771137", "favorite_count": 0, "tweet_hashtags": ["BombSyria", "BombSyria", "BombSyria", "BombSyria"]},{"lang": "en", "created_at": "2015-011-28T20:00:40Z", "tweet_urls": [], "entities": [], "text_en": "Hope you've all got plenty of money saved then ,cos its your money they will cut to pay for all this carnage #BombSyria", "concepts": [], "retweet_count": 0, "id": "670693812126277632", "favorite_count": 0, "tweet_hashtags": ["BombSyria"]},{"lang": "en", "created_at": "2015-011-28T18:57:58Z", "tweet_urls": [], "entities": [], "text_en": "RT @DavesAstronomy: #DontBombSyria #BombSyria  the question should be which is the bigger crime, bombing in syria, or doing nothing? Either\u2026", "concepts": [], "retweet_count": 1, "id": "670678031715966976", "favorite_count": 0, "tweet_hashtags": ["DontBombSyria", "BombSyria"]},{"lang": "en", "created_at": "2015-011-28T18:21:19Z", "tweet_urls": [], "entities": [], "text_en": "RT @BrexitBulldog: So shocked #DontBombSyria is trending. How anyone could be opposed to the destruction of a terrorist regime is beyond me\u2026", "concepts": [], "retweet_count": 34, "id": "670668810303766528", "favorite_count": 0, "tweet_hashtags": ["DontBombSyria", "BombSyria", "BombIS"]},{"lang": "en", "created_at": "2015-011-28T22:09:07Z", "tweet_urls": [], "entities": [], "text_en": "RT @tuco_tuco: This is BAE systems share price over the last month. BAE systems is the UKs biggest weapons manufacturer \n#BombSyria https:/\u2026", "concepts": [], "retweet_count": 13, "id": "670726136972902400", "favorite_count": 0, "tweet_hashtags": ["BombSyria"]},{"lang": "en", "created_at": "2015-011-28T18:31:00Z", "tweet_urls": [], "entities": [], "text_en": "RT @TomBoxingAsylum: Imagine some of these fannies lived in the 40s. \"Oh, lets not bomb the German's, it's so inhuman\".  #Weirdos #BombSyria", "concepts": [], "retweet_count": 31, "id": "670671248125489156", "favorite_count": 0, "tweet_hashtags": ["Weirdos", "BombSyria"]},{"lang": "en", "created_at": "2015-011-28T21:01:24Z", "tweet_urls": [], "entities": [], "text_en": "For the love of God, #BombSyria If not now then you will be bombing your own country by 2017 There is no negotiating with terrorists", "concepts": [], "retweet_count": 0, "id": "670709096983711744", "favorite_count": 0, "tweet_hashtags": ["BombSyria"]},{"lang": "en", "created_at": "2015-011-28T18:35:58Z", "tweet_urls": [], "entities": [], "text_en": "RT @Petercwray: Time to #bombsyria, diplomatic route you say? These people behead aid workers and bury children alive. By all means let's b\u2026", "concepts": [], "retweet_count": 1, "id": "670672498418171904", "favorite_count": 0, "tweet_hashtags": ["bombsyria"]},{"lang": "en", "created_at": "2015-011-28T21:46:25Z", "tweet_urls": [], "entities": [], "text_en": "RT @uwakreations: OH! Please @jeremycorbyn @JeremyCorbyn4PM STAND your ground! We r FULLY behind you! We WILL NOT #BombSyria #DontBombSyria\u2026", "concepts": [], "retweet_count": 8, "id": "670720426859974656", "favorite_count": 0, "tweet_hashtags": ["BombSyria", "DontBombSyria"]}]