[{"lang": "en", "created_at": "2015-011-30T23:58:10Z", "tweet_urls": [], "entities": ["US"], "text_en": "RT @Bonn1eGreer: Finally, ladies &amp;gentlemen, here's Cam to US network re: #syriaairstrikes:\n\"Well, of course, I always want to bring my Par\u2026", "concepts": [], "retweet_count": 22, "id": "671478358069391360", "favorite_count": 0, "tweet_hashtags": ["syriaairstrikes"]},{"lang": "en", "created_at": "2015-011-30T23:47:08Z", "tweet_urls": ["http://bit.ly/1juMIsX"], "entities": ["Syria"], "text_en": "RT @CatherineWest1: I will be voting against air strikes in #Syria. Here is my full statement: https://t.co/AtQu4115hw #SyriaAirStrikes #Sy\u2026", "concepts": [], "retweet_count": 709, "id": "671475578592194560", "favorite_count": 0, "tweet_hashtags": ["Syria", "SyriaAirStrikes", "SyriaVote"]},{"lang": "en", "created_at": "2015-011-30T23:54:59Z", "tweet_urls": [], "entities": ["uk", "syria", "britain"], "text_en": "Yes to #uk #britain #AirStrikes #syria #syriaairstrikes wipe them all out. \u2708\ufe0f\ud83d\udca3\ud83d\udca3\ud83d\udca3 #YesAirstrikeSyria #wipeoutisis #evilislam extremists", "concepts": [], "retweet_count": 0, "id": "671477556009377792", "favorite_count": 0, "tweet_hashtags": ["uk", "britain", "AirStrikes", "syria", "syriaairstrikes", "YesAirstrikeSyria", "wipeoutisis", "evilislam"]},{"lang": "en", "created_at": "2015-011-30T23:55:00Z", "tweet_urls": ["http://bit.ly/1juMIsX"], "entities": ["Syria"], "text_en": "RT @CatherineWest1: I will be voting against air strikes in #Syria. Here is my full statement: https://t.co/AtQu4115hw #SyriaAirStrikes #Sy\u2026", "concepts": [], "retweet_count": 709, "id": "671477561818521600", "favorite_count": 0, "tweet_hashtags": ["Syria", "SyriaAirStrikes", "SyriaVote"]},{"lang": "en", "created_at": "2015-011-30T23:49:57Z", "tweet_urls": [], "entities": [], "text_en": "RT @Marc_Geoffrey: 17 minutes of #newsnight spent making #syriaairstrikes about @UKLabour and just 3 minutes on @David_Cameron's quest to t\u2026", "concepts": [], "retweet_count": 16, "id": "671476290063630336", "favorite_count": 0, "tweet_hashtags": ["newsnight", "syriaairstrikes"]},{"lang": "en", "created_at": "2015-011-30T23:38:09Z", "tweet_urls": [], "entities": ["RachaelMaskell"], "text_en": "_RT_ YorkMomentum: Huge applause at RachaelMaskell announcement that she'll be voting against #syriaairstrikes on weds #RachaelSyriaDebate", "concepts": [], "retweet_count": 0, "id": "671473321201016833", "favorite_count": 0, "tweet_hashtags": ["syriaairstrikes", "RachaelSyriaDebate"]},{"lang": "en", "created_at": "2015-011-30T23:47:50Z", "tweet_urls": [], "entities": [], "text_en": "RT @An_Phoblacht: 'The Cycle of International Stupidity' is topical as people debate #Syria #syriaairstrikes #ISIS #ISIL https://t.co/BJWqq\u2026", "concepts": [], "retweet_count": 25, "id": "671475755130486784", "favorite_count": 0, "tweet_hashtags": ["Syria", "syriaairstrikes", "ISIS", "ISIL"]},{"lang": "en", "created_at": "2015-011-30T23:48:29Z", "tweet_urls": [], "entities": ["Afghanistan", "Libya", "Iraq"], "text_en": "@LouieWoodall Yes, but as hamfistedly and disastrously as #Afghanistan , #Iraq &amp; #Libya . Media &amp; politicians won't learn. #syriaairstrikes", "concepts": [], "retweet_count": 0, "id": "671475920520257536", "favorite_count": 0, "tweet_hashtags": ["Afghanistan", "Iraq", "Libya", "syriaairstrikes"]},{"lang": "en", "created_at": "2015-011-30T23:54:23Z", "tweet_urls": ["http://bit.ly/1juMIsX"], "entities": ["Syria"], "text_en": "RT @CatherineWest1: I will be voting against air strikes in #Syria. Here is my full statement: https://t.co/AtQu4115hw #SyriaAirStrikes #Sy\u2026", "concepts": [], "retweet_count": 709, "id": "671477406264393728", "favorite_count": 0, "tweet_hashtags": ["Syria", "SyriaAirStrikes", "SyriaVote"]},{"lang": "en", "created_at": "2015-011-30T23:50:17Z", "tweet_urls": [], "entities": [], "text_en": "RT @OwenThompson: Can confirm I will not be voting to bomb #Syria - bombing alone will not solve issues in the region #syriaairstrikes", "concepts": ["Bomb"], "retweet_count": 442, "id": "671476374713016320", "favorite_count": 0, "tweet_hashtags": ["Syria", "syriaairstrikes"]},{"lang": "en", "created_at": "2015-011-30T23:54:23Z", "tweet_urls": ["http://bit.ly/1juMIsX"], "entities": ["Syria"], "text_en": "RT @CatherineWest1: I will be voting against air strikes in #Syria. Here is my full statement: https://t.co/AtQu4115hw #SyriaAirStrikes #Sy\u2026", "concepts": [], "retweet_count": 709, "id": "671477403517116417", "favorite_count": 0, "tweet_hashtags": ["Syria", "SyriaAirStrikes", "SyriaVote"]},{"lang": "en", "created_at": "2015-011-30T23:46:14Z", "tweet_urls": [], "entities": [], "text_en": "RT @OwenThompson: Can confirm I will not be voting to bomb #Syria - bombing alone will not solve issues in the region #syriaairstrikes", "concepts": ["Bomb"], "retweet_count": 442, "id": "671475355149066240", "favorite_count": 0, "tweet_hashtags": ["Syria", "syriaairstrikes"]},{"lang": "en", "created_at": "2015-011-30T23:55:12Z", "tweet_urls": [], "entities": ["US"], "text_en": "RT @Bonn1eGreer: Finally, ladies &amp;gentlemen, here's Cam to US network re: #syriaairstrikes:\n\"Well, of course, I always want to bring my Par\u2026", "concepts": [], "retweet_count": 22, "id": "671477609998495744", "favorite_count": 0, "tweet_hashtags": ["syriaairstrikes"]},{"lang": "en", "created_at": "2015-011-30T23:56:13Z", "tweet_urls": ["http://bit.ly/1juMIsX"], "entities": ["Syria"], "text_en": "RT @CatherineWest1: I will be voting against air strikes in #Syria. Here is my full statement: https://t.co/AtQu4115hw #SyriaAirStrikes #Sy\u2026", "concepts": [], "retweet_count": 709, "id": "671477866358534144", "favorite_count": 0, "tweet_hashtags": ["Syria", "SyriaAirStrikes", "SyriaVote"]},{"lang": "en", "created_at": "2015-011-30T23:44:44Z", "tweet_urls": [], "entities": [], "text_en": "Doesn't #DavidCameron realise #syriaairstrikes will only result in the slaughter of thousands of innocent people??? #dontbombsyria", "concepts": [], "retweet_count": 0, "id": "671474976134926336", "favorite_count": 0, "tweet_hashtags": ["DavidCameron", "syriaairstrikes", "dontbombsyria"]},{"lang": "en", "created_at": "2015-011-30T23:53:46Z", "tweet_urls": [], "entities": [], "text_en": "RT @OwenThompson: Can confirm I will not be voting to bomb #Syria - bombing alone will not solve issues in the region #syriaairstrikes", "concepts": ["Bomb"], "retweet_count": 442, "id": "671477249993015297", "favorite_count": 0, "tweet_hashtags": ["Syria", "syriaairstrikes"]},{"lang": "en", "created_at": "2015-011-30T23:38:49Z", "tweet_urls": [], "entities": ["Middle East"], "text_en": "RT @JamesMelville: Bombing the Middle East hasn't removed the threat of terrorism, it has increased the threat.\n#Syria #syriaairstrikes htt\u2026", "concepts": ["Middle East", "Asia", "Near East", "Far East", "Arabic language", "Orientalism"], "retweet_count": 565, "id": "671473486368514048", "favorite_count": 0, "tweet_hashtags": ["Syria", "syriaairstrikes"]},{"lang": "en", "created_at": "2015-011-30T23:53:07Z", "tweet_urls": [], "entities": [], "text_en": "RT @OwenThompson: Can confirm I will not be voting to bomb #Syria - bombing alone will not solve issues in the region #syriaairstrikes", "concepts": ["Bomb"], "retweet_count": 442, "id": "671477084963905536", "favorite_count": 0, "tweet_hashtags": ["Syria", "syriaairstrikes"]},{"lang": "en", "created_at": "2015-011-30T23:50:31Z", "tweet_urls": [], "entities": [], "text_en": "RT @OwenThompson: Can confirm I will not be voting to bomb #Syria - bombing alone will not solve issues in the region #syriaairstrikes", "concepts": ["Bomb"], "retweet_count": 442, "id": "671476431587835905", "favorite_count": 0, "tweet_hashtags": ["Syria", "syriaairstrikes"]},{"lang": "en", "created_at": "2015-011-30T23:47:51Z", "tweet_urls": ["http://bit.ly/1juMIsX"], "entities": ["Syria"], "text_en": "RT @CatherineWest1: I will be voting against air strikes in #Syria. Here is my full statement: https://t.co/AtQu4115hw #SyriaAirStrikes #Sy\u2026", "concepts": [], "retweet_count": 709, "id": "671475760897662977", "favorite_count": 0, "tweet_hashtags": ["Syria", "SyriaAirStrikes", "SyriaVote"]},{"lang": "en", "created_at": "2015-011-30T23:46:51Z", "tweet_urls": [], "entities": [], "text_en": "RT @broadcastscot: .@TommySheppard quite brilliant in the @HouseofCommons tonight. Clearly set out issues and why @theSNP will vote against\u2026", "concepts": [], "retweet_count": 17, "id": "671475511290421248", "favorite_count": 0, "tweet_hashtags": ["syriaairstrikes"]},{"lang": "en", "created_at": "2015-011-30T23:41:07Z", "tweet_urls": [], "entities": [], "text_en": "RT @OwenThompson: Can confirm I will not be voting to bomb #Syria - bombing alone will not solve issues in the region #syriaairstrikes", "concepts": ["Bomb"], "retweet_count": 442, "id": "671474065828421633", "favorite_count": 0, "tweet_hashtags": ["Syria", "syriaairstrikes"]},{"lang": "en", "created_at": "2015-011-30T23:45:29Z", "tweet_urls": [], "entities": [], "text_en": "RT @OwenThompson: Can confirm I will not be voting to bomb #Syria - bombing alone will not solve issues in the region #syriaairstrikes", "concepts": ["Bomb"], "retweet_count": 442, "id": "671475165704921088", "favorite_count": 0, "tweet_hashtags": ["Syria", "syriaairstrikes"]},{"lang": "en", "created_at": "2015-011-30T23:48:21Z", "tweet_urls": [], "entities": [], "text_en": "RT @RichBri10: Does no one care about illegally invading another country's SOVEREIGNTY  #syriaairstrikes  ? #newsnight", "concepts": ["Sovereign state", "United States"], "retweet_count": 5, "id": "671475888672911361", "favorite_count": 0, "tweet_hashtags": ["syriaairstrikes", "newsnight"]},{"lang": "en", "created_at": "2015-011-30T23:48:32Z", "tweet_urls": [], "entities": ["Paris"], "text_en": "#syriaairstrikes \n\nIs bombing worth the consequences of Syrian Terror attacks on our own streets. Paris is the prime example.\nGotta learn.", "concepts": ["The Streets"], "retweet_count": 0, "id": "671475934139142144", "favorite_count": 0, "tweet_hashtags": ["syriaairstrikes"]},{"lang": "en", "created_at": "2015-011-30T23:40:29Z", "tweet_urls": [], "entities": [], "text_en": ".@AndyMcDonaldMP great piece - letter to my mp today: unanswered questions about #syriaairstrikes  https://t.co/JRSmp8vypP", "concepts": [], "retweet_count": 2, "id": "671473907640217601", "favorite_count": 2, "tweet_hashtags": ["syriaairstrikes"]},{"lang": "en", "created_at": "2015-011-30T23:42:01Z", "tweet_urls": [], "entities": [], "text_en": "The #labourparty looks weak, ineffective and badly led tonight. A disastrous two weeks #syriaairstrikes", "concepts": [], "retweet_count": 0, "id": "671474293461671936", "favorite_count": 0, "tweet_hashtags": ["labourparty", "syriaairstrikes"]},{"lang": "en", "created_at": "2015-011-30T23:37:58Z", "tweet_urls": [], "entities": ["Middle East"], "text_en": "RT @JamesMelville: Bombing the Middle East hasn't removed the threat of terrorism, it has increased the threat.\n#Syria #syriaairstrikes htt\u2026", "concepts": ["Middle East", "Asia", "Near East", "Far East", "Arabic language", "Orientalism"], "retweet_count": 565, "id": "671473273440485376", "favorite_count": 0, "tweet_hashtags": ["Syria", "syriaairstrikes"]},{"lang": "en", "created_at": "2015-011-30T23:45:27Z", "tweet_urls": [], "entities": ["Jo Stevens", "Andy Slaughter"], "text_en": "MPs Jo Stevens and Andy Slaughter to vote against #syriaairstrikes #DontBombSyria", "concepts": ["Israel", "1960 births"], "retweet_count": 0, "id": "671475158503317504", "favorite_count": 0, "tweet_hashtags": ["syriaairstrikes", "DontBombSyria"]},{"lang": "en", "created_at": "2015-011-30T23:54:11Z", "tweet_urls": [], "entities": [], "text_en": "RT @OwenThompson: Can confirm I will not be voting to bomb #Syria - bombing alone will not solve issues in the region #syriaairstrikes", "concepts": ["Bomb"], "retweet_count": 442, "id": "671477354133344256", "favorite_count": 0, "tweet_hashtags": ["Syria", "syriaairstrikes"]},{"lang": "en", "created_at": "2015-011-30T23:39:16Z", "tweet_urls": [], "entities": ["Middle East"], "text_en": "RT @JamesMelville: Bombing the Middle East hasn't removed the threat of terrorism, it has increased the threat.\n#Syria #syriaairstrikes htt\u2026", "concepts": ["Middle East", "Asia", "Near East", "Far East", "Arabic language", "Orientalism"], "retweet_count": 565, "id": "671473599111421952", "favorite_count": 0, "tweet_hashtags": ["Syria", "syriaairstrikes"]},{"lang": "en", "created_at": "2015-011-30T23:42:22Z", "tweet_urls": [], "entities": ["Syria"], "text_en": "Lots of ppl against bombing Syria. If it's wrong then what is the answer? How do we deal with ISIS? #syriaairstrikes", "concepts": ["Iraq War"], "retweet_count": 0, "id": "671474381571366912", "favorite_count": 0, "tweet_hashtags": ["syriaairstrikes"]},{"lang": "en", "created_at": "2015-011-30T23:52:43Z", "tweet_urls": [], "entities": [], "text_en": "RT @OwenThompson: Can confirm I will not be voting to bomb #Syria - bombing alone will not solve issues in the region #syriaairstrikes", "concepts": ["Bomb"], "retweet_count": 442, "id": "671476987526033412", "favorite_count": 0, "tweet_hashtags": ["Syria", "syriaairstrikes"]},{"lang": "en", "created_at": "2015-011-30T23:38:59Z", "tweet_urls": [], "entities": [], "text_en": "RT @YorkMomentum: Huge applause at @RachaelMaskell announcement that she'll be voting against #syriaairstrikes on weds #RachaelSyriaDebate", "concepts": [], "retweet_count": 33, "id": "671473527602683904", "favorite_count": 0, "tweet_hashtags": ["syriaairstrikes", "RachaelSyriaDebate"]},{"lang": "en", "created_at": "2015-011-30T23:43:52Z", "tweet_urls": [], "entities": [], "text_en": "Lets get this straight. The only ones to blame for #syriaairstrikes are those who vote to #BombSyria. No one is forcing them. #DontBombSyria", "concepts": ["The Only Ones"], "retweet_count": 0, "id": "671474759159410688", "favorite_count": 1, "tweet_hashtags": ["syriaairstrikes", "BombSyria", "DontBombSyria"]},{"lang": "en", "created_at": "2015-011-30T23:41:20Z", "tweet_urls": ["http://bit.ly/1juMIsX"], "entities": ["Syria"], "text_en": "RT @CatherineWest1: I will be voting against air strikes in #Syria. Here is my full statement: https://t.co/AtQu4115hw #SyriaAirStrikes #Sy\u2026", "concepts": [], "retweet_count": 709, "id": "671474120454983680", "favorite_count": 0, "tweet_hashtags": ["Syria", "SyriaAirStrikes", "SyriaVote"]},{"lang": "en", "created_at": "2015-011-30T23:46:03Z", "tweet_urls": [], "entities": [], "text_en": "RT @OwenThompson: Can confirm I will not be voting to bomb #Syria - bombing alone will not solve issues in the region #syriaairstrikes", "concepts": ["Bomb"], "retweet_count": 442, "id": "671475308260913153", "favorite_count": 0, "tweet_hashtags": ["Syria", "syriaairstrikes"]},{"lang": "en", "created_at": "2015-011-30T23:55:41Z", "tweet_urls": [], "entities": [], "text_en": "@rushanaraali please vote for #NoWar #syriaairstrikes #notosyriaairstrikes", "concepts": [], "retweet_count": 0, "id": "671477732908339200", "favorite_count": 2, "tweet_hashtags": ["NoWar", "syriaairstrikes", "notosyriaairstrikes"]},{"lang": "en", "created_at": "2015-011-30T23:37:19Z", "tweet_urls": ["http://www.thenational.scot/news/nato-general-sir-richard-shirreff-warns-air-strikes-on-syria-are-useless.10604"], "entities": ["Nato", "Sir Richard Shirreff", "Syria"], "text_en": "RT @ArmstrongM: Nato general Sir Richard Shirreff warns Syria air strikes useless #DontBombSyria @PaulBlomfieldMP #syriaairstrikes  https:/\u2026", "concepts": ["NATO"], "retweet_count": 3, "id": "671473110646988800", "favorite_count": 0, "tweet_hashtags": ["DontBombSyria", "syriaairstrikes"]},{"lang": "en", "created_at": "2015-011-30T23:48:07Z", "tweet_urls": ["http://bit.ly/1juMIsX"], "entities": ["Syria"], "text_en": "RT @CatherineWest1: I will be voting against air strikes in #Syria. Here is my full statement: https://t.co/AtQu4115hw #SyriaAirStrikes #Sy\u2026", "concepts": [], "retweet_count": 709, "id": "671475827385737216", "favorite_count": 0, "tweet_hashtags": ["Syria", "SyriaAirStrikes", "SyriaVote"]},{"lang": "en", "created_at": "2015-011-30T23:40:30Z", "tweet_urls": [], "entities": ["Dave"], "text_en": "RT @trikyd: So, our bombs are more accurate than any the Americans &amp; French have, are they Dave? #newsnight #syriaairstrikes", "concepts": ["Louisiana", "Russia", "English language"], "retweet_count": 22, "id": "671473913256394752", "favorite_count": 0, "tweet_hashtags": ["newsnight", "syriaairstrikes"]},{"lang": "en", "created_at": "2015-011-30T23:39:15Z", "tweet_urls": [], "entities": ["Dave"], "text_en": "RT @michaelnixon70: Hope Dave does a flying visit to the cheer on the 70'000 moderates once the bombs have done the trick.\n#Syria #syriaair\u2026", "concepts": ["Bj\u00f6rk", "English-language films"], "retweet_count": 3, "id": "671473594933878784", "favorite_count": 0, "tweet_hashtags": ["Syria", "syriaairstrikes"]},{"lang": "en", "created_at": "2015-011-30T23:56:41Z", "tweet_urls": [], "entities": [], "text_en": "RT @OwenThompson: Can confirm I will not be voting to bomb #Syria - bombing alone will not solve issues in the region #syriaairstrikes", "concepts": ["Bomb"], "retweet_count": 442, "id": "671477982301696001", "favorite_count": 0, "tweet_hashtags": ["Syria", "syriaairstrikes"]},{"lang": "en", "created_at": "2015-011-30T23:45:13Z", "tweet_urls": [], "entities": ["Middle East"], "text_en": "RT @JamesMelville: Bombing the Middle East hasn't removed the threat of terrorism, it has increased the threat.\n#Syria #syriaairstrikes htt\u2026", "concepts": ["Middle East", "Asia", "Near East", "Far East", "Arabic language", "Orientalism"], "retweet_count": 565, "id": "671475096708653056", "favorite_count": 0, "tweet_hashtags": ["Syria", "syriaairstrikes"]},{"lang": "en", "created_at": "2015-011-30T23:43:43Z", "tweet_urls": [], "entities": [], "text_en": "RT @YorkMomentum: Huge applause at @RachaelMaskell announcement that she'll be voting against #syriaairstrikes on weds #RachaelSyriaDebate", "concepts": [], "retweet_count": 33, "id": "671474720156622852", "favorite_count": 0, "tweet_hashtags": ["syriaairstrikes", "RachaelSyriaDebate"]},{"lang": "en", "created_at": "2015-011-30T23:38:29Z", "tweet_urls": [], "entities": ["Middle East"], "text_en": "RT @JamesMelville: Bombing the Middle East hasn't removed the threat of terrorism, it has increased the threat.\n#Syria #syriaairstrikes htt\u2026", "concepts": ["Middle East", "Asia", "Near East", "Far East", "Arabic language", "Orientalism"], "retweet_count": 565, "id": "671473402067165184", "favorite_count": 0, "tweet_hashtags": ["Syria", "syriaairstrikes"]},{"lang": "en", "created_at": "2015-011-30T23:45:27Z", "tweet_urls": [], "entities": [], "text_en": "RT @messagewords: Of course #syriaairstrikes are tempting. Our brains like simple answers. But what kinds of magic will parliament put its \u2026", "concepts": ["Music of Atlanta, Georgia"], "retweet_count": 1, "id": "671475157689630720", "favorite_count": 0, "tweet_hashtags": ["syriaairstrikes"]},{"lang": "en", "created_at": "2015-011-30T23:47:15Z", "tweet_urls": [], "entities": [], "text_en": "RT @emmanuel_gold5: Will @SimonDanczuk vote with his Tory paymasters and agree to bomb the extended families of many of his constituents? \n\u2026", "concepts": ["Extended family", "Family"], "retweet_count": 1, "id": "671475610913492992", "favorite_count": 0, "tweet_hashtags": ["syriaairstrikes"]},{"lang": "en", "created_at": "2015-011-30T23:42:35Z", "tweet_urls": ["http://bit.ly/1juMIsX"], "entities": ["Syria"], "text_en": "RT @CatherineWest1: I will be voting against air strikes in #Syria. Here is my full statement: https://t.co/AtQu4115hw #SyriaAirStrikes #Sy\u2026", "concepts": [], "retweet_count": 709, "id": "671474436848111617", "favorite_count": 0, "tweet_hashtags": ["Syria", "SyriaAirStrikes", "SyriaVote"]},{"lang": "en", "created_at": "2015-011-30T23:45:27Z", "tweet_urls": [], "entities": [], "text_en": "RT @YorkMomentum: Huge applause at @RachaelMaskell announcement that she'll be voting against #syriaairstrikes on weds #RachaelSyriaDebate", "concepts": [], "retweet_count": 33, "id": "671475155332411393", "favorite_count": 0, "tweet_hashtags": ["syriaairstrikes", "RachaelSyriaDebate"]},{"lang": "en", "created_at": "2015-011-30T23:47:47Z", "tweet_urls": [], "entities": ["Isis"], "text_en": "RT @BrookesTimes: My cartoon Saturday @TheTimes. Isis is a barbaric death cult...what about some of our allies? #syriaairstrikes https://t.\u2026", "concepts": ["United Nations", "Hardcore punk"], "retweet_count": 4684, "id": "671475745651314689", "favorite_count": 0, "tweet_hashtags": ["syriaairstrikes"]},{"lang": "en", "created_at": "2015-011-30T23:53:46Z", "tweet_urls": ["http://www.bbc.co.uk/news/uk-politics-34970516"], "entities": ["Syria", "David Cameron"], "text_en": "Syria air strikes vote on Wednesday, says David Cameron #syriaairstrikes #voteno  https://t.co/SSr02CSdJo", "concepts": ["Israel", "Yom Kippur War"], "retweet_count": 0, "id": "671477249334472709", "favorite_count": 0, "tweet_hashtags": ["syriaairstrikes", "voteno"]},{"lang": "fr", "retweet_count": 0, "created_at": "2015-011-30T08:10:15Z", "tweet_urls": ["https://petition.parliament.uk/petitions/113064"], "entities": ["SignPetition"], "concepts": [], "text_fr": "SignPetition: Don't bomb Syria https://t.co/bki0MCGSgn #DontBombSyria #syriaairstrikes #SyrianRefugees #BombSyria #noairstrikes #NotInMyName", "id": "671239806349914112", "favorite_count": 0, "tweet_hashtags": ["DontBombSyria", "syriaairstrikes", "SyrianRefugees", "BombSyria", "noairstrikes", "NotInMyName"]},{"lang": "en", "created_at": "2015-011-30T23:41:33Z", "tweet_urls": [], "entities": [], "text_en": "RT @Marc_Geoffrey: @JackieKane @LobbyComm I'll be doing the same after #Newsnight #DontBombSyria #SyriaAirStrikes", "concepts": [], "retweet_count": 1, "id": "671474175274573824", "favorite_count": 0, "tweet_hashtags": ["Newsnight", "DontBombSyria", "SyriaAirStrikes"]},{"lang": "en", "created_at": "2015-011-30T23:47:14Z", "tweet_urls": [], "entities": ["Middle East"], "text_en": "RT @JamesMelville: Bombing the Middle East hasn't removed the threat of terrorism, it has increased the threat.\n#Syria #syriaairstrikes htt\u2026", "concepts": ["Middle East", "Asia", "Near East", "Far East", "Arabic language", "Orientalism"], "retweet_count": 565, "id": "671475607444811777", "favorite_count": 0, "tweet_hashtags": ["Syria", "syriaairstrikes"]},{"lang": "en", "created_at": "2015-011-30T23:59:55Z", "tweet_urls": ["http://www.theyworkforyou.com"], "entities": [], "text_en": "It only takes 3 minutes to write to your MP to tell them what you think about #syriaairstrikes - contact them via https://t.co/midiZWu4VL", "concepts": [], "retweet_count": 0, "id": "671478798110597120", "favorite_count": 0, "tweet_hashtags": ["syriaairstrikes"]},{"lang": "en", "created_at": "2015-011-30T23:41:31Z", "tweet_urls": ["http://bit.ly/1juMIsX"], "entities": ["Syria"], "text_en": "RT @CatherineWest1: I will be voting against air strikes in #Syria. Here is my full statement: https://t.co/AtQu4115hw #SyriaAirStrikes #Sy\u2026", "concepts": [], "retweet_count": 709, "id": "671474166273605633", "favorite_count": 0, "tweet_hashtags": ["Syria", "SyriaAirStrikes", "SyriaVote"]},{"lang": "en", "created_at": "2015-011-30T23:48:54Z", "tweet_urls": [], "entities": ["Middle East"], "text_en": "RT @JamesMelville: Bombing the Middle East hasn't removed the threat of terrorism, it has increased the threat.\n#Syria #syriaairstrikes htt\u2026", "concepts": ["Middle East", "Asia", "Near East", "Far East", "Arabic language", "Orientalism"], "retweet_count": 565, "id": "671476024362868736", "favorite_count": 0, "tweet_hashtags": ["Syria", "syriaairstrikes"]},{"lang": "en", "created_at": "2015-011-30T23:50:19Z", "tweet_urls": ["http://ln.is/leadersoftheopposition.com/ChRmC"], "entities": [], "text_en": "RT @lotopposition: Our editorial team opposes #syriaairstrikes, and this article explains why. Consideration is desperately needed.\n\nhttps:\u2026", "concepts": [], "retweet_count": 9, "id": "671476383210672128", "favorite_count": 0, "tweet_hashtags": ["syriaairstrikes"]},{"lang": "en", "created_at": "2015-011-30T23:38:28Z", "tweet_urls": [], "entities": [], "text_en": "There's still a possibility that all the attacks on #Corbyn might turn all the pro #syriaairstrikes @UKLabour MPs into voting no #bbcpapers", "concepts": ["Attack", "Attack!"], "retweet_count": 0, "id": "671473397973544960", "favorite_count": 0, "tweet_hashtags": ["Corbyn", "syriaairstrikes", "bbcpapers"]},{"lang": "en", "created_at": "2015-011-30T23:59:29Z", "tweet_urls": [], "entities": ["US"], "text_en": "RT @Bonn1eGreer: Finally, ladies &amp;gentlemen, here's Cam to US network re: #syriaairstrikes:\n\"Well, of course, I always want to bring my Par\u2026", "concepts": [], "retweet_count": 22, "id": "671478688580567040", "favorite_count": 0, "tweet_hashtags": ["syriaairstrikes"]},{"lang": "en", "created_at": "2015-011-30T23:59:57Z", "tweet_urls": [], "entities": ["Cameron"], "text_en": "RT @defencechris: #syriaairstrikes debate and #vote Weds. Cameron statement soon.", "concepts": [], "retweet_count": 1, "id": "671478805786173440", "favorite_count": 0, "tweet_hashtags": ["syriaairstrikes", "vote"]},{"lang": "en", "created_at": "2015-011-30T23:56:26Z", "tweet_urls": ["http://bit.ly/1juMIsX"], "entities": ["Syria"], "text_en": "RT @CatherineWest1: I will be voting against air strikes in #Syria. Here is my full statement: https://t.co/AtQu4115hw #SyriaAirStrikes #Sy\u2026", "concepts": [], "retweet_count": 709, "id": "671477922918739968", "favorite_count": 0, "tweet_hashtags": ["Syria", "SyriaAirStrikes", "SyriaVote"]},{"lang": "en", "created_at": "2015-011-30T23:58:44Z", "tweet_urls": [], "entities": ["Syria"], "text_en": ".@SteveReedMP What have your CLP and constituents asked you to do on #Syria vote? And how will you vote? #syriaairstrikes @UKLabour", "concepts": [], "retweet_count": 2, "id": "671478499874619392", "favorite_count": 2, "tweet_hashtags": ["Syria", "syriaairstrikes"]},{"lang": "en", "created_at": "2015-011-30T23:55:45Z", "tweet_urls": ["http://bit.ly/1juMIsX"], "entities": ["Syria"], "text_en": "RT @CatherineWest1: I will be voting against air strikes in #Syria. Here is my full statement: https://t.co/AtQu4115hw #SyriaAirStrikes #Sy\u2026", "concepts": [], "retweet_count": 709, "id": "671477747953348608", "favorite_count": 0, "tweet_hashtags": ["Syria", "SyriaAirStrikes", "SyriaVote"]},{"lang": "en", "created_at": "2015-011-30T23:51:22Z", "tweet_urls": ["http://www.thenational.scot/news/nato-general-sir-richard-shirreff-warns-air-strikes-on-syria-are-useless.10604"], "entities": ["Nato", "Sir Richard Shirreff", "Syria"], "text_en": "RT @ArmstrongM: Nato general Sir Richard Shirreff warns Syria air strikes useless #DontBombSyria @PaulBlomfieldMP #syriaairstrikes  https:/\u2026", "concepts": ["NATO"], "retweet_count": 3, "id": "671476645337956354", "favorite_count": 0, "tweet_hashtags": ["DontBombSyria", "syriaairstrikes"]},{"lang": "en", "created_at": "2015-011-30T23:46:29Z", "tweet_urls": [], "entities": [], "text_en": "RT @OwenThompson: Can confirm I will not be voting to bomb #Syria - bombing alone will not solve issues in the region #syriaairstrikes", "concepts": ["Bomb"], "retweet_count": 442, "id": "671475418688593920", "favorite_count": 0, "tweet_hashtags": ["Syria", "syriaairstrikes"]},{"lang": "fr", "retweet_count": 3, "created_at": "2015-011-30T16:36:46Z", "tweet_urls": [], "entities": ["Syria."], "concepts": ["Refugee", "Lebanon"], "text_fr": "RT @BrownIsNewBlack: #Yarmouk refugee camp, Syria. #syriaairstrikes #syria #DontBombSyria https://t.co/oTLJHT8JqE", "id": "671367274641661952", "favorite_count": 0, "tweet_hashtags": ["Yarmouk", "syriaairstrikes", "syria", "DontBombSyria"]},{"lang": "en", "created_at": "2015-011-30T23:49:48Z", "tweet_urls": [], "entities": [], "text_en": "RT @Marc_Geoffrey: 17 minutes of #newsnight spent making #syriaairstrikes about @UKLabour and just 3 minutes on @David_Cameron's quest to t\u2026", "concepts": [], "retweet_count": 16, "id": "671476250003795969", "favorite_count": 0, "tweet_hashtags": ["newsnight", "syriaairstrikes"]},{"lang": "en", "created_at": "2015-011-30T23:47:31Z", "tweet_urls": [], "entities": [], "text_en": "RT @YorkMomentum: Huge applause at @RachaelMaskell announcement that she'll be voting against #syriaairstrikes on weds #RachaelSyriaDebate", "concepts": [], "retweet_count": 33, "id": "671475678148206592", "favorite_count": 0, "tweet_hashtags": ["syriaairstrikes", "RachaelSyriaDebate"]},{"lang": "en", "created_at": "2015-011-30T23:42:49Z", "tweet_urls": [], "entities": [], "text_en": "RT @OwenThompson: Can confirm I will not be voting to bomb #Syria - bombing alone will not solve issues in the region #syriaairstrikes", "concepts": ["Bomb"], "retweet_count": 442, "id": "671474493534130176", "favorite_count": 0, "tweet_hashtags": ["Syria", "syriaairstrikes"]},{"lang": "en", "created_at": "2015-011-30T23:42:21Z", "tweet_urls": [], "entities": ["Middle East"], "text_en": "RT @JamesMelville: Bombing the Middle East hasn't removed the threat of terrorism, it has increased the threat.\n#Syria #syriaairstrikes htt\u2026", "concepts": ["Middle East", "Asia", "Near East", "Far East", "Arabic language", "Orientalism"], "retweet_count": 565, "id": "671474378727641088", "favorite_count": 0, "tweet_hashtags": ["Syria", "syriaairstrikes"]},{"lang": "en", "created_at": "2015-011-30T23:38:38Z", "tweet_urls": ["http://bit.ly/1juMIsX"], "entities": ["Syria"], "text_en": "RT @CatherineWest1: I will be voting against air strikes in #Syria. Here is my full statement: https://t.co/AtQu4115hw #SyriaAirStrikes #Sy\u2026", "concepts": [], "retweet_count": 709, "id": "671473440176611328", "favorite_count": 0, "tweet_hashtags": ["Syria", "SyriaAirStrikes", "SyriaVote"]},{"lang": "de", "text_de": "Vorschlag: wie w\u00e4re es damit als Plakat f\u00fcr die n\u00e4chste Wahl ? der Ehrlichkeit halber #Merkel #Irak #syriaairstrikes https://t.co/CNgtar99Zk", "created_at": "2015-011-30T19:35:05Z", "tweet_urls": [], "entities": [], "concepts": [], "retweet_count": 0, "id": "671412148418035713", "favorite_count": 0, "tweet_hashtags": ["Merkel", "Irak", "syriaairstrikes"]},{"lang": "en", "created_at": "2015-011-30T23:45:45Z", "tweet_urls": [], "entities": [], "text_en": "RT @OwenThompson: Can confirm I will not be voting to bomb #Syria - bombing alone will not solve issues in the region #syriaairstrikes", "concepts": ["Bomb"], "retweet_count": 442, "id": "671475232507609088", "favorite_count": 0, "tweet_hashtags": ["Syria", "syriaairstrikes"]},{"lang": "en", "created_at": "2015-011-30T23:57:27Z", "tweet_urls": [], "entities": [], "text_en": "RT @OwenThompson: Can confirm I will not be voting to bomb #Syria - bombing alone will not solve issues in the region #syriaairstrikes", "concepts": ["Bomb"], "retweet_count": 442, "id": "671478176623775744", "favorite_count": 0, "tweet_hashtags": ["Syria", "syriaairstrikes"]},{"lang": "en", "created_at": "2015-011-30T23:47:03Z", "tweet_urls": [], "entities": ["BBC"], "text_en": "@BBCNormanS Still no policy to report? When did you become Head Political Drama? Quite a team you have there.  :) #BBC #syriaairstrikes", "concepts": ["The A-Team", "Political science"], "retweet_count": 0, "id": "671475560028241922", "favorite_count": 0, "tweet_hashtags": ["BBC", "syriaairstrikes"]},{"lang": "en", "created_at": "2015-011-30T23:43:28Z", "tweet_urls": [], "entities": [], "text_en": "RT @YorkMomentum: Huge applause at @RachaelMaskell announcement that she'll be voting against #syriaairstrikes on weds #RachaelSyriaDebate", "concepts": [], "retweet_count": 33, "id": "671474658907185152", "favorite_count": 0, "tweet_hashtags": ["syriaairstrikes", "RachaelSyriaDebate"]},{"lang": "en", "created_at": "2015-011-30T23:40:15Z", "tweet_urls": [], "entities": [], "text_en": "RT @Marc_Geoffrey: 17 minutes of #newsnight spent making #syriaairstrikes about @UKLabour and just 3 minutes on @David_Cameron's quest to t\u2026", "concepts": [], "retweet_count": 16, "id": "671473847045091328", "favorite_count": 0, "tweet_hashtags": ["newsnight", "syriaairstrikes"]},{"lang": "en", "created_at": "2015-011-30T23:52:24Z", "tweet_urls": [], "entities": ["Corbyn"], "text_en": "It's a sensitive subject &amp; granted we must act carefully, but Corbyn's so called 'action' of pacifism is NOT the solution! #SyriaAirStrikes", "concepts": ["Allegation", "Pleading", "Legal terms"], "retweet_count": 0, "id": "671476907871969280", "favorite_count": 0, "tweet_hashtags": ["SyriaAirStrikes"]},{"lang": "en", "created_at": "2015-011-30T23:49:19Z", "tweet_urls": [], "entities": [], "text_en": "RT @OwenThompson: Can confirm I will not be voting to bomb #Syria - bombing alone will not solve issues in the region #syriaairstrikes", "concepts": ["Bomb"], "retweet_count": 442, "id": "671476132156411904", "favorite_count": 0, "tweet_hashtags": ["Syria", "syriaairstrikes"]},{"lang": "en", "created_at": "2015-011-30T23:45:03Z", "tweet_urls": [], "entities": [], "text_en": "RT @OwenThompson: Can confirm I will not be voting to bomb #Syria - bombing alone will not solve issues in the region #syriaairstrikes", "concepts": ["Bomb"], "retweet_count": 442, "id": "671475056384581632", "favorite_count": 0, "tweet_hashtags": ["Syria", "syriaairstrikes"]},{"lang": "en", "created_at": "2015-011-30T23:37:48Z", "tweet_urls": ["https://twitter.com/suttonnick/status/671443710626938880"], "entities": [], "text_en": "RT @WgrahameW: How on earth is this headline even 1% true? Is #corbyn to blame for #syriaairstrikes even though he's against them? https://\u2026", "concepts": ["Kurt Cobain"], "retweet_count": 3, "id": "671473231212257284", "favorite_count": 0, "tweet_hashtags": ["corbyn", "syriaairstrikes"]},{"lang": "en", "created_at": "2015-011-30T23:53:25Z", "tweet_urls": [], "entities": [], "text_en": "RT @OwenThompson: Can confirm I will not be voting to bomb #Syria - bombing alone will not solve issues in the region #syriaairstrikes", "concepts": ["Bomb"], "retweet_count": 442, "id": "671477163288317952", "favorite_count": 0, "tweet_hashtags": ["Syria", "syriaairstrikes"]},{"lang": "en", "created_at": "2015-011-30T23:46:22Z", "tweet_urls": [], "entities": [], "text_en": "Does no one care about illegally invading another country's SOVEREIGNTY  #syriaairstrikes  ? #newsnight", "concepts": ["Sovereign state", "United States"], "retweet_count": 5, "id": "671475389798227969", "favorite_count": 2, "tweet_hashtags": ["syriaairstrikes", "newsnight"]},{"lang": "en", "created_at": "2015-011-30T23:51:06Z", "tweet_urls": [], "entities": [], "text_en": "RT @OwenThompson: Can confirm I will not be voting to bomb #Syria - bombing alone will not solve issues in the region #syriaairstrikes", "concepts": ["Bomb"], "retweet_count": 442, "id": "671476580993146880", "favorite_count": 0, "tweet_hashtags": ["Syria", "syriaairstrikes"]},{"lang": "en", "created_at": "2015-011-30T23:53:42Z", "tweet_urls": ["http://bit.ly/1juMIsX"], "entities": ["Syria"], "text_en": "RT @CatherineWest1: I will be voting against air strikes in #Syria. Here is my full statement: https://t.co/AtQu4115hw #SyriaAirStrikes #Sy\u2026", "concepts": [], "retweet_count": 709, "id": "671477232938954752", "favorite_count": 0, "tweet_hashtags": ["Syria", "SyriaAirStrikes", "SyriaVote"]},{"lang": "en", "created_at": "2015-011-30T23:56:01Z", "tweet_urls": [], "entities": ["syria."], "text_en": "Watch the @bbcdoctorwho episode #TheZygonInvasion to know that we shouldn't be bombing #syria. #syriaairstrikes", "concepts": [], "retweet_count": 0, "id": "671477817843036160", "favorite_count": 0, "tweet_hashtags": ["TheZygonInvasion", "syria", "syriaairstrikes"]},{"lang": "en", "created_at": "2015-011-30T23:47:56Z", "tweet_urls": ["http://bit.ly/1juMIsX"], "entities": ["Syria"], "text_en": "RT @CatherineWest1: I will be voting against air strikes in #Syria. Here is my full statement: https://t.co/AtQu4115hw #SyriaAirStrikes #Sy\u2026", "concepts": [], "retweet_count": 709, "id": "671475780086603776", "favorite_count": 0, "tweet_hashtags": ["Syria", "SyriaAirStrikes", "SyriaVote"]},{"lang": "en", "created_at": "2015-011-30T23:54:10Z", "tweet_urls": [], "entities": [], "text_en": "Sad to see @OwenSmith_MP on #newsnight showing beyond doubt that the #labourparty has no policy on #syriaairstrikes . Utter shambles", "concepts": [], "retweet_count": 0, "id": "671477350136209408", "favorite_count": 0, "tweet_hashtags": ["newsnight", "labourparty", "syriaairstrikes"]},{"lang": "en", "created_at": "2015-011-30T23:37:59Z", "tweet_urls": ["http://bit.ly/21k1Z1L"], "entities": ["US", "Syria"], "text_en": "RT @telesurenglish: Report finds US airstrikes did kill 6 children in Syria https://t.co/XMwwL75NNC #syriaairstrikes https://t.co/MHdbzm1nUw", "concepts": [], "retweet_count": 80, "id": "671473280025542657", "favorite_count": 0, "tweet_hashtags": ["syriaairstrikes"]},{"lang": "en", "created_at": "2015-011-30T23:54:45Z", "tweet_urls": [], "entities": [], "text_en": "RT @OwenThompson: Can confirm I will not be voting to bomb #Syria - bombing alone will not solve issues in the region #syriaairstrikes", "concepts": ["Bomb"], "retweet_count": 442, "id": "671477497196867584", "favorite_count": 0, "tweet_hashtags": ["Syria", "syriaairstrikes"]},{"lang": "en", "created_at": "2015-011-30T23:52:06Z", "tweet_urls": ["https://medium.com/@mtpennycook/british-airstrikes-against-daesh-in-syria-a0f14c7b0ba1#.3gl0faueo"], "entities": [], "text_en": "RT @Bonn1eGreer: A #freevote-gives us the mind and the measure of the #PLP.\n\"I intend to vote against #syriaairstrikes\"-@mtpennycook\nhttps:\u2026", "concepts": [], "retweet_count": 17, "id": "671476828972916736", "favorite_count": 0, "tweet_hashtags": ["freevote", "PLP", "syriaairstrikes"]},{"lang": "en", "created_at": "2015-011-30T23:38:42Z", "tweet_urls": ["https://twitter.com/suttonnick/status/671443710626938880"], "entities": [], "text_en": "RT @WgrahameW: How on earth is this headline even 1% true? Is #corbyn to blame for #syriaairstrikes even though he's against them? https://\u2026", "concepts": ["Kurt Cobain"], "retweet_count": 3, "id": "671473459067789317", "favorite_count": 0, "tweet_hashtags": ["corbyn", "syriaairstrikes"]},{"lang": "en", "created_at": "2015-011-30T23:44:07Z", "tweet_urls": [], "entities": [], "text_en": "Will Tory MPs be getting a free vote? #syriaairstrikes", "concepts": ["Voting"], "retweet_count": 0, "id": "671474819913904130", "favorite_count": 0, "tweet_hashtags": ["syriaairstrikes"]},{"lang": "en", "created_at": "2015-011-30T23:46:00Z", "tweet_urls": ["http://youtu.be/kSZMTyI4wVE"], "entities": [], "text_en": "Blur - Don't Bomb When You're The Bomb #syriaairstrikes  https://t.co/NYwjB4twCk", "concepts": [], "retweet_count": 0, "id": "671475293698310145", "favorite_count": 0, "tweet_hashtags": ["syriaairstrikes"]},{"lang": "en", "created_at": "2015-011-30T23:39:24Z", "tweet_urls": [], "entities": [], "text_en": "RT @nikrozee: #theoneshow is the bbc pro bombing now? #syriaairstrikes @BBCOne", "concepts": ["BBC", "BBC Online", "ITV"], "retweet_count": 2, "id": "671473633932496896", "favorite_count": 0, "tweet_hashtags": ["theoneshow", "syriaairstrikes"]},{"lang": "en", "created_at": "2015-011-30T23:46:20Z", "tweet_urls": [], "entities": [], "text_en": "Will @SimonDanczuk vote with his Tory paymasters and agree to bomb the extended families of many of his constituents? \n\n#syriaairstrikes", "concepts": ["Extended family", "Family"], "retweet_count": 1, "id": "671475377454346240", "favorite_count": 2, "tweet_hashtags": ["syriaairstrikes"]},{"lang": "en", "created_at": "2015-011-30T23:54:01Z", "tweet_urls": ["http://bit.ly/1juMIsX"], "entities": ["Syria"], "text_en": "RT @CatherineWest1: I will be voting against air strikes in #Syria. Here is my full statement: https://t.co/AtQu4115hw #SyriaAirStrikes #Sy\u2026", "concepts": [], "retweet_count": 709, "id": "671477313612201984", "favorite_count": 0, "tweet_hashtags": ["Syria", "SyriaAirStrikes", "SyriaVote"]},{"lang": "en", "created_at": "2015-011-30T23:47:04Z", "tweet_urls": [], "entities": ["Blair"], "text_en": "RT @CllrJonSHarvey: I think @jeremycorbyn has been extraordinarily generous in giving PLP a free vote on #syriaairstrikes - Blair put a 3 l\u2026", "concepts": ["Voting"], "retweet_count": 33, "id": "671475564574830592", "favorite_count": 0, "tweet_hashtags": ["syriaairstrikes"]},{"lang": "en", "created_at": "2015-011-30T23:54:00Z", "tweet_urls": ["http://bit.ly/1juMIsX"], "entities": ["Syria"], "text_en": "RT @CatherineWest1: I will be voting against air strikes in #Syria. Here is my full statement: https://t.co/AtQu4115hw #SyriaAirStrikes #Sy\u2026", "concepts": [], "retweet_count": 709, "id": "671477307043901441", "favorite_count": 0, "tweet_hashtags": ["Syria", "SyriaAirStrikes", "SyriaVote"]},{"lang": "en", "created_at": "2015-011-30T23:40:16Z", "tweet_urls": [], "entities": [], "text_en": "RT @OwenThompson: Can confirm I will not be voting to bomb #Syria - bombing alone will not solve issues in the region #syriaairstrikes", "concepts": ["Bomb"], "retweet_count": 442, "id": "671473852325736448", "favorite_count": 0, "tweet_hashtags": ["Syria", "syriaairstrikes"]},{"lang": "en", "created_at": "2015-011-30T23:52:35Z", "tweet_urls": ["http://bit.ly/1juMIsX"], "entities": ["Syria"], "text_en": "RT @CatherineWest1: I will be voting against air strikes in #Syria. Here is my full statement: https://t.co/AtQu4115hw #SyriaAirStrikes #Sy\u2026", "concepts": [], "retweet_count": 709, "id": "671476953577336833", "favorite_count": 0, "tweet_hashtags": ["Syria", "SyriaAirStrikes", "SyriaVote"]}]